Workbook

Sheet Dashboard
A1: SkillLance Operations Database
A2: Summary of customers, paid enrollments, sales, affiliate commissions, and payouts.
A5: Customers | D5: Active enrollments | G5: Paid course revenue | J5: Available affiliate payout
A6: =COUNTA(Customers!$A$5:$A$504) -> 1 | D6: =COUNTIFS(Enrollments!$I$5:$I$504,"Granted") -> 1 | G6: =SUMIFS(Sales!$G$5:$G$504,Sales!$H$5:$H$504,"Paid") -> 9999 | J6: =SUM(Affiliates!$J$5:$J$504) -> 0
A9: Sales and commission | B9: Amount | D9: Database controls | E9: Value | G9: Data entry order
A10: Paid sales | B10: =COUNTIFS(Sales!$H$5:$H$504,"Paid") -> 1 | D10: Affiliate commission rate | E10: 0.7 | G10: 1 | H10: Add or update customer details on Customers
A11: Paid course revenue | B11: =SUMIFS(Sales!$G$5:$G$504,Sales!$H$5:$H$504,"Paid") -> 9999 | D11: Minimum payout | E11: 500 | G11: 2 | H11: Record the paid course purchase in Sales
A12: Approved affiliate commission | B12: =SUMIFS(Sales!$K$5:$K$504,Sales!$L$5:$L$504,"Approved") -> 6999.3 | D12: Login user ID | E12: Customer e-mail | G12: 3 | H12: Grant course access in Enrollments
A13: Paid affiliate payouts | B13: =SUMIFS(Payouts!$G$5:$G$504,Payouts!$H$5:$H$504,"Paid") -> 0 | D13: Password storage | E13: Do not store passwords | G13: 4 | H13: Create the affiliate record and referral code
A14: Commission awaiting payout | B14: =SUM(Affiliates!$J$5:$J$504) -> 0 | D14: Sales source | E14: Razorpay payment export | G14: 5 | H14: Record payout payments after approval

Sheet Customers
A1: Customers
A2: One row per learner. Their e-mail is also their affiliate dashboard user ID.
A4: Customer ID | B4: Created date | C4: Full name | D4: E-mail | E4: Mobile no. | F4: State | G4: Login user ID | H4: Account status | I4: Password setup | J4: Notes
A5: SKLC0001 | B5: 46322 | C5: Shivam Kumar Jha | D5: iamshivamjha4u@gmail.com | E5: 9873149873 | F5: Delhi | G5: =IF(D5="","",D5) -> iamshivamjha4u@gmail.com | H5: Active | I5: Set
G6: =IF(D6="","",D6)
G7: =IF(D7="","",D7)
G8: =IF(D8="","",D8)
G9: =IF(D9="","",D9)
G10: =IF(D10="","",D10)
G11: =IF(D11="","",D11)
G12: =IF(D12="","",D12)
G13: =IF(D13="","",D13)
G14: =IF(D14="","",D14)
G15: =IF(D15="","",D15)
G16: =IF(D16="","",D16)
G17: =IF(D17="","",D17)
... G504: =IF(D504="","",D504)

Sheet Enrollments
A1: Enrollments
A2: Record course access separately from the Razorpay sale so learning access can be managed clearly.
A4: Enrollment ID | B4: Enrollment date | C4: Customer ID | D4: Course ID | E4: Course name | F4: Course price | G4: Payment status | H4: Payment ID | I4: Course access | J4: Login issued date | K4: Notes
A5: SLCS0001 | B5: 46322 | C5: SKLC0001 | D5: FINANCE | E5: =IF(D5="","",VLOOKUP(D5,Courses!$A$5:$G$10,2,FALSE)) -> Finance Package | F5: =IF(D5="","",VLOOKUP(D5,Courses!$A$5:$G$10,3,FALSE)) -> 9999 | G5: Paid | H5: pay_Tsu0UbvRH2mByr | I5: Granted | J5: 46322
E6: =IF(D6="","",VLOOKUP(D6,Courses!$A$5:$G$10,2,FALSE)) | F6: =IF(D6="","",VLOOKUP(D6,Courses!$A$5:$G$10,3,FALSE))
E7: =IF(D7="","",VLOOKUP(D7,Courses!$A$5:$G$10,2,FALSE)) | F7: =IF(D7="","",VLOOKUP(D7,Courses!$A$5:$G$10,3,FALSE))
E8: =IF(D8="","",VLOOKUP(D8,Courses!$A$5:$G$10,2,FALSE)) | F8: =IF(D8="","",VLOOKUP(D8,Courses!$A$5:$G$10,3,FALSE))
E9: =IF(D9="","",VLOOKUP(D9,Courses!$A$5:$G$10,2,FALSE)) | F9: =IF(D9="","",VLOOKUP(D9,Courses!$A$5:$G$10,3,FALSE))
E10: =IF(D10="","",VLOOKUP(D10,Courses!$A$5:$G$10,2,FALSE)) | F10: =IF(D10="","",VLOOKUP(D10,Courses!$A$5:$G$10,3,FALSE))
E11: =IF(D11="","",VLOOKUP(D11,Courses!$A$5:$G$10,2,FALSE)) | F11: =IF(D11="","",VLOOKUP(D11,Courses!$A$5:$G$10,3,FALSE))
E12: =IF(D12="","",VLOOKUP(D12,Courses!$A$5:$G$10,2,FALSE)) | F12: =IF(D12="","",VLOOKUP(D12,Courses!$A$5:$G$10,3,FALSE))
E13: =IF(D13="","",VLOOKUP(D13,Courses!$A$5:$G$10,2,FALSE)) | F13: =IF(D13="","",VLOOKUP(D13,Courses!$A$5:$G$10,3,FALSE))
E14: =IF(D14="","",VLOOKUP(D14,Courses!$A$5:$G$10,2,FALSE)) | F14: =IF(D14="","",VLOOKUP(D14,Courses!$A$5:$G$10,3,FALSE))
E15: =IF(D15="","",VLOOKUP(D15,Courses!$A$5:$G$10,2,FALSE)) | F15: =IF(D15="","",VLOOKUP(D15,Courses!$A$5:$G$10,3,FALSE))
E16: =IF(D16="","",VLOOKUP(D16,Courses!$A$5:$G$10,2,FALSE)) | F16: =IF(D16="","",VLOOKUP(D16,Courses!$A$5:$G$10,3,FALSE))
E17: =IF(D17="","",VLOOKUP(D17,Courses!$A$5:$G$10,2,FALSE)) | F17: =IF(D17="","",VLOOKUP(D17,Courses!$A$5:$G$10,3,FALSE))
... E504: =IF(D504="","",VLOOKUP(D504,Courses!$A$5:$G$10,2,FALSE)) | F504: =IF(D504="","",VLOOKUP(D504,Courses!$A$5:$G$10,3,FALSE))

Sheet Courses
A1: Courses
A2: Current SkillLance package pricing, Razorpay payment button IDs, and the affiliate commission rate.
A4: Course ID | B4: Course name | C4: Price | D4: Course count | E4: Razorpay payment button ID | F4: Affiliate commission rate | G4: Commission per sale
A5: ELITE | B5: Elite Package | C5: 699 | D5: 8 | E5: pl_TsbhUucoFI4Zwq | F5: 0.7 | G5: =C5*F5 -> 489.3
A6: MARKETING | B6: Marketing Mastery | C6: 1499 | D6: 2 | E6: pl_Tsc0RtshcVOlv4 | F6: 0.7 | G6: =C6*F6 -> 1049.3
A7: SOFT | B7: Soft Skill Mastery | C7: 2599 | D7: 2 | E7: pl_Tsc6SWIstwLyX9 | F7: 0.7 | G7: =C7*F7 -> 1819.3
A8: PRO | B8: Pro Package | C8: 4999 | D8: 4 | E8: pl_TscASQMDiKuLXb | F8: 0.7 | G8: =C8*F8 -> 3499.3
A9: PRIME | B9: Prime Package | C9: 7499 | D9: 6 | E9: pl_Tscrao7delyrCN | F9: 0.7 | G9: =C9*F9 -> 5249.3
A10: FINANCE | B10: Finance Package | C10: 9999 | D10: 3 | E10: pl_Tsd2sXzAgnBo2g | F10: 0.7 | G10: =C10*F10 -> 6999.3

Sheet Sales
A1: Sales
A2: Enter each Razorpay payment once. Commission amounts calculate only for paid sales with a referrer affiliate ID.
A4: Sale ID | B4: Razorpay payment ID | C4: Sale date | D4: Customer ID | E4: Course ID | F4: Course name | G4: Course price | H4: Payment status | I4: Referrer affiliate ID | J4: Commission rate | K4: Commission amount | L4: Commission status | M4: Notes
A5: SALE000001 | B5: pay_Tsu0UbvRH2mByr | C5: 46322 | D5: SKLC0001 | E5: FINANCE | F5: =IF(E5="","",VLOOKUP(E5,Courses!$A$5:$G$10,2,FALSE)) -> Finance Package | G5: =IF(E5="","",VLOOKUP(E5,Courses!$A$5:$G$10,3,FALSE)) -> 9999 | H5: Paid | I5: Skilllanceprp01 | J5: =IF(I5="","",VLOOKUP(E5,Courses!$A$5:$G$10,6,FALSE)) -> 0.7 | K5: =IF(AND(H5="Paid",I5<>""),G5*J5,0) -> 6999.3 | L5: Approved
F6: =IF(E6="","",VLOOKUP(E6,Courses!$A$5:$G$10,2,FALSE)) | G6: =IF(E6="","",VLOOKUP(E6,Courses!$A$5:$G$10,3,FALSE)) | J6: =IF(I6="","",VLOOKUP(E6,Courses!$A$5:$G$10,6,FALSE)) | K6: =IF(AND(H6="Paid",I6<>""),G6*J6,0) -> 0
F7: =IF(E7="","",VLOOKUP(E7,Courses!$A$5:$G$10,2,FALSE)) | G7: =IF(E7="","",VLOOKUP(E7,Courses!$A$5:$G$10,3,FALSE)) | J7: =IF(I7="","",VLOOKUP(E7,Courses!$A$5:$G$10,6,FALSE)) | K7: =IF(AND(H7="Paid",I7<>""),G7*J7,0) -> 0
F8: =IF(E8="","",VLOOKUP(E8,Courses!$A$5:$G$10,2,FALSE)) | G8: =IF(E8="","",VLOOKUP(E8,Courses!$A$5:$G$10,3,FALSE)) | J8: =IF(I8="","",VLOOKUP(E8,Courses!$A$5:$G$10,6,FALSE)) | K8: =IF(AND(H8="Paid",I8<>""),G8*J8,0) -> 0
F9: =IF(E9="","",VLOOKUP(E9,Courses!$A$5:$G$10,2,FALSE)) | G9: =IF(E9="","",VLOOKUP(E9,Courses!$A$5:$G$10,3,FALSE)) | J9: =IF(I9="","",VLOOKUP(E9,Courses!$A$5:$G$10,6,FALSE)) | K9: =IF(AND(H9="Paid",I9<>""),G9*J9,0) -> 0
F10: =IF(E10="","",VLOOKUP(E10,Courses!$A$5:$G$10,2,FALSE)) | G10: =IF(E10="","",VLOOKUP(E10,Courses!$A$5:$G$10,3,FALSE)) | J10: =IF(I10="","",VLOOKUP(E10,Courses!$A$5:$G$10,6,FALSE)) | K10: =IF(AND(H10="Paid",I10<>""),G10*J10,0) -> 0
F11: =IF(E11="","",VLOOKUP(E11,Courses!$A$5:$G$10,2,FALSE)) | G11: =IF(E11="","",VLOOKUP(E11,Courses!$A$5:$G$10,3,FALSE)) | J11: =IF(I11="","",VLOOKUP(E11,Courses!$A$5:$G$10,6,FALSE)) | K11: =IF(AND(H11="Paid",I11<>""),G11*J11,0) -> 0
F12: =IF(E12="","",VLOOKUP(E12,Courses!$A$5:$G$10,2,FALSE)) | G12: =IF(E12="","",VLOOKUP(E12,Courses!$A$5:$G$10,3,FALSE)) | J12: =IF(I12="","",VLOOKUP(E12,Courses!$A$5:$G$10,6,FALSE)) | K12: =IF(AND(H12="Paid",I12<>""),G12*J12,0) -> 0
F13: =IF(E13="","",VLOOKUP(E13,Courses!$A$5:$G$10,2,FALSE)) | G13: =IF(E13="","",VLOOKUP(E13,Courses!$A$5:$G$10,3,FALSE)) | J13: =IF(I13="","",VLOOKUP(E13,Courses!$A$5:$G$10,6,FALSE)) | K13: =IF(AND(H13="Paid",I13<>""),G13*J13,0) -> 0
F14: =IF(E14="","",VLOOKUP(E14,Courses!$A$5:$G$10,2,FALSE)) | G14: =IF(E14="","",VLOOKUP(E14,Courses!$A$5:$G$10,3,FALSE)) | J14: =IF(I14="","",VLOOKUP(E14,Courses!$A$5:$G$10,6,FALSE)) | K14: =IF(AND(H14="Paid",I14<>""),G14*J14,0) -> 0
F15: =IF(E15="","",VLOOKUP(E15,Courses!$A$5:$G$10,2,FALSE)) | G15: =IF(E15="","",VLOOKUP(E15,Courses!$A$5:$G$10,3,FALSE)) | J15: =IF(I15="","",VLOOKUP(E15,Courses!$A$5:$G$10,6,FALSE)) | K15: =IF(AND(H15="Paid",I15<>""),G15*J15,0) -> 0
F16: =IF(E16="","",VLOOKUP(E16,Courses!$A$5:$G$10,2,FALSE)) | G16: =IF(E16="","",VLOOKUP(E16,Courses!$A$5:$G$10,3,FALSE)) | J16: =IF(I16="","",VLOOKUP(E16,Courses!$A$5:$G$10,6,FALSE)) | K16: =IF(AND(H16="Paid",I16<>""),G16*J16,0) -> 0
F17: =IF(E17="","",VLOOKUP(E17,Courses!$A$5:$G$10,2,FALSE)) | G17: =IF(E17="","",VLOOKUP(E17,Courses!$A$5:$G$10,3,FALSE)) | J17: =IF(I17="","",VLOOKUP(E17,Courses!$A$5:$G$10,6,FALSE)) | K17: =IF(AND(H17="Paid",I17<>""),G17*J17,0) -> 0
... F504: =IF(E504="","",VLOOKUP(E504,Courses!$A$5:$G$10,2,FALSE)) | G504: =IF(E504="","",VLOOKUP(E504,Courses!$A$5:$G$10,3,FALSE)) | J504: =IF(I504="","",VLOOKUP(E504,Courses!$A$5:$G$10,6,FALSE)) | K504: =IF(AND(H504="Paid",I504<>""),G504*J504,0) -> 0

Sheet Affiliates
A1: Affiliates
A2: Use the customer e-mail as the dashboard user ID. Do not record plain-text passwords in this workbook.
A4: Affiliate ID | B4: Customer ID | C4: Affiliate name | D4: User ID / e-mail | E4: Referral code | F4: Approved date | G4: Affiliate status | H4: Approved commission | I4: Paid out | J4: Available payout | K4: Payout method | L4: Payout address
A5: =+Customers!C5 -> Shivam Kumar Jha | B5: =+Customers!A5 -> SKLC0001 | C5: =IF(B5="","",VLOOKUP(B5,Customers!$A$5:$J$504,3,FALSE)) -> Shivam Kumar Jha | D5: =IF(B5="","",VLOOKUP(B5,Customers!$A$5:$J$504,4,FALSE)) -> iamshivamjha4u@gmail.com | E5: ?ref=SKILLLANCE01 | F5: 46322 | G5: Active | H5: =IF(A5="","",SUMIFS(Sales!$K$5:$K$504,Sales!$I$5:$I$504,A5,Sales!$L$5:$L$504,"Approved")) -> 0 | I5: =IF(A5="","",SUMIFS(Payouts!$G$5:$G$504,Payouts!$B$5:$B$504,A5,Payouts!$H$5:$H$504,"Paid")) -> 0 | J5: =IF(A5="","",H5-I5) -> 0
C6: =IF(B6="","",VLOOKUP(B6,Customers!$A$5:$J$504,3,FALSE)) | D6: =IF(B6="","",VLOOKUP(B6,Customers!$A$5:$J$504,4,FALSE)) | H6: =IF(A6="","",SUMIFS(Sales!$K$5:$K$504,Sales!$I$5:$I$504,A6,Sales!$L$5:$L$504,"Approved")) | I6: =IF(A6="","",SUMIFS(Payouts!$G$5:$G$504,Payouts!$B$5:$B$504,A6,Payouts!$H$5:$H$504,"Paid")) | J6: =IF(A6="","",H6-I6)
C7: =IF(B7="","",VLOOKUP(B7,Customers!$A$5:$J$504,3,FALSE)) | D7: =IF(B7="","",VLOOKUP(B7,Customers!$A$5:$J$504,4,FALSE)) | H7: =IF(A7="","",SUMIFS(Sales!$K$5:$K$504,Sales!$I$5:$I$504,A7,Sales!$L$5:$L$504,"Approved")) | I7: =IF(A7="","",SUMIFS(Payouts!$G$5:$G$504,Payouts!$B$5:$B$504,A7,Payouts!$H$5:$H$504,"Paid")) | J7: =IF(A7="","",H7-I7)
C8: =IF(B8="","",VLOOKUP(B8,Customers!$A$5:$J$504,3,FALSE)) | D8: =IF(B8="","",VLOOKUP(B8,Customers!$A$5:$J$504,4,FALSE)) | H8: =IF(A8="","",SUMIFS(Sales!$K$5:$K$504,Sales!$I$5:$I$504,A8,Sales!$L$5:$L$504,"Approved")) | I8: =IF(A8="","",SUMIFS(Payouts!$G$5:$G$504,Payouts!$B$5:$B$504,A8,Payouts!$H$5:$H$504,"Paid")) | J8: =IF(A8="","",H8-I8)
C9: =IF(B9="","",VLOOKUP(B9,Customers!$A$5:$J$504,3,FALSE)) | D9: =IF(B9="","",VLOOKUP(B9,Customers!$A$5:$J$504,4,FALSE)) | H9: =IF(A9="","",SUMIFS(Sales!$K$5:$K$504,Sales!$I$5:$I$504,A9,Sales!$L$5:$L$504,"Approved")) | I9: =IF(A9="","",SUMIFS(Payouts!$G$5:$G$504,Payouts!$B$5:$B$504,A9,Payouts!$H$5:$H$504,"Paid")) | J9: =IF(A9="","",H9-I9)
C10: =IF(B10="","",VLOOKUP(B10,Customers!$A$5:$J$504,3,FALSE)) | D10: =IF(B10="","",VLOOKUP(B10,Customers!$A$5:$J$504,4,FALSE)) | H10: =IF(A10="","",SUMIFS(Sales!$K$5:$K$504,Sales!$I$5:$I$504,A10,Sales!$L$5:$L$504,"Approved")) | I10: =IF(A10="","",SUMIFS(Payouts!$G$5:$G$504,Payouts!$B$5:$B$504,A10,Payouts!$H$5:$H$504,"Paid")) | J10: =IF(A10="","",H10-I10)
C11: =IF(B11="","",VLOOKUP(B11,Customers!$A$5:$J$504,3,FALSE)) | D11: =IF(B11="","",VLOOKUP(B11,Customers!$A$5:$J$504,4,FALSE)) | H11: =IF(A11="","",SUMIFS(Sales!$K$5:$K$504,Sales!$I$5:$I$504,A11,Sales!$L$5:$L$504,"Approved")) | I11: =IF(A11="","",SUMIFS(Payouts!$G$5:$G$504,Payouts!$B$5:$B$504,A11,Payouts!$H$5:$H$504,"Paid")) | J11: =IF(A11="","",H11-I11)
C12: =IF(B12="","",VLOOKUP(B12,Customers!$A$5:$J$504,3,FALSE)) | D12: =IF(B12="","",VLOOKUP(B12,Customers!$A$5:$J$504,4,FALSE)) | H12: =IF(A12="","",SUMIFS(Sales!$K$5:$K$504,Sales!$I$5:$I$504,A12,Sales!$L$5:$L$504,"Approved")) | I12: =IF(A12="","",SUMIFS(Payouts!$G$5:$G$504,Payouts!$B$5:$B$504,A12,Payouts!$H$5:$H$504,"Paid")) | J12: =IF(A12="","",H12-I12)
C13: =IF(B13="","",VLOOKUP(B13,Customers!$A$5:$J$504,3,FALSE)) | D13: =IF(B13="","",VLOOKUP(B13,Customers!$A$5:$J$504,4,FALSE)) | H13: =IF(A13="","",SUMIFS(Sales!$K$5:$K$504,Sales!$I$5:$I$504,A13,Sales!$L$5:$L$504,"Approved")) | I13: =IF(A13="","",SUMIFS(Payouts!$G$5:$G$504,Payouts!$B$5:$B$504,A13,Payouts!$H$5:$H$504,"Paid")) | J13: =IF(A13="","",H13-I13)
C14: =IF(B14="","",VLOOKUP(B14,Customers!$A$5:$J$504,3,FALSE)) | D14: =IF(B14="","",VLOOKUP(B14,Customers!$A$5:$J$504,4,FALSE)) | H14: =IF(A14="","",SUMIFS(Sales!$K$5:$K$504,Sales!$I$5:$I$504,A14,Sales!$L$5:$L$504,"Approved")) | I14: =IF(A14="","",SUMIFS(Payouts!$G$5:$G$504,Payouts!$B$5:$B$504,A14,Payouts!$H$5:$H$504,"Paid")) | J14: =IF(A14="","",H14-I14)
C15: =IF(B15="","",VLOOKUP(B15,Customers!$A$5:$J$504,3,FALSE)) | D15: =IF(B15="","",VLOOKUP(B15,Customers!$A$5:$J$504,4,FALSE)) | H15: =IF(A15="","",SUMIFS(Sales!$K$5:$K$504,Sales!$I$5:$I$504,A15,Sales!$L$5:$L$504,"Approved")) | I15: =IF(A15="","",SUMIFS(Payouts!$G$5:$G$504,Payouts!$B$5:$B$504,A15,Payouts!$H$5:$H$504,"Paid")) | J15: =IF(A15="","",H15-I15)
C16: =IF(B16="","",VLOOKUP(B16,Customers!$A$5:$J$504,3,FALSE)) | D16: =IF(B16="","",VLOOKUP(B16,Customers!$A$5:$J$504,4,FALSE)) | H16: =IF(A16="","",SUMIFS(Sales!$K$5:$K$504,Sales!$I$5:$I$504,A16,Sales!$L$5:$L$504,"Approved")) | I16: =IF(A16="","",SUMIFS(Payouts!$G$5:$G$504,Payouts!$B$5:$B$504,A16,Payouts!$H$5:$H$504,"Paid")) | J16: =IF(A16="","",H16-I16)
C17: =IF(B17="","",VLOOKUP(B17,Customers!$A$5:$J$504,3,FALSE)) | D17: =IF(B17="","",VLOOKUP(B17,Customers!$A$5:$J$504,4,FALSE)) | H17: =IF(A17="","",SUMIFS(Sales!$K$5:$K$504,Sales!$I$5:$I$504,A17,Sales!$L$5:$L$504,"Approved")) | I17: =IF(A17="","",SUMIFS(Payouts!$G$5:$G$504,Payouts!$B$5:$B$504,A17,Payouts!$H$5:$H$504,"Paid")) | J17: =IF(A17="","",H17-I17)
... C504: =IF(B504="","",VLOOKUP(B504,Customers!$A$5:$J$504,3,FALSE)) | D504: =IF(B504="","",VLOOKUP(B504,Customers!$A$5:$J$504,4,FALSE)) | H504: =IF(A504="","",SUMIFS(Sales!$K$5:$K$504,Sales!$I$5:$I$504,A504,Sales!$L$5:$L$504,"Approved")) | I504: =IF(A504="","",SUMIFS(Payouts!$G$5:$G$504,Payouts!$B$5:$B$504,A504,Payouts!$H$5:$H$504,"Paid")) | J504: =IF(A504="","",H504-I504)

Sheet Payouts
A1: Payouts
A2: Record each affiliate payout only after approval. The payment reference is required for reconciliation.
A4: Payout ID | B4: Affiliate ID | C4: Request date | D4: Period start | E4: Period end | F4: Approved commission | G4: Amount paid | H4: Payout status | I4: Payment reference | J4: Processed date | K4: Notes

Sheet Lists
A1: Lists
A2: Controlled values used by the drop-down fields in the database sheets.
A4: Account status | B4: Password setup | C4: Payment status | D4: Course access | E4: Commission status | F4: Affiliate status | G4: Payout status | H4: Payout method
A5: Active | B5: Not sent | C5: Pending | D5: Not granted | E5: Pending | F5: Active | G5: Requested | H5: UPI
A6: Inactive | B6: Sent | C6: Paid | D6: Granted | E6: Approved | F6: Paused | G6: Approved | H6: Bank transfer
A7: Blocked | B7: Set | C7: Failed | D7: Revoked | E7: Paid | F7: Blocked | G7: Paid | H7: Other
B8: Reset requested | C8: Refunded | E8: Cancelled | G8: Rejected
